LICENSE
README.md
setup.py
fskmodem/__init__.py
fskmodem/modem.py
fskmodem.egg-info/PKG-INFO
fskmodem.egg-info/SOURCES.txt
fskmodem.egg-info/dependency_links.txt
fskmodem.egg-info/top_level.txt