Metadata-Version: 2.1
Name: fskmodem
Version: 0.1.0
Summary: Full duplex FSK modem
Home-page: https://github.com/simplyequipped/fskmodem
Author: Simply Equipped LLC
Author-email: howard@simplyequipped.com
License: UNKNOWN
Platform: UNKNOWN
Classifier: Programming Language :: Python :: 3
Classifier: License :: OSI Approved :: MIT License
Classifier: Operating System :: OS Independent
Requires-Python: >=3.6
License-File: LICENSE
